bellapy/__init__.py
bellapy/cli/__init__.py
bellapy/cli/data_cli.py
bellapy/cli/main.py
bellapy/data/__init__.py
bellapy/data/augmentation.py
bellapy/data/batch.py
bellapy/data/cleaning.py
bellapy/data/cost.py
bellapy/data/diff.py
bellapy/data/export.py
bellapy/data/filters.py
bellapy/data/formats.py
bellapy/data/processors.py
bellapy/data/prompts.py
bellapy/data/sampling.py
bellapy/data/validation.py
bellapy/dpo/__init__.py
bellapy/inference/__init__.py
bellapy/integrations/__init__.py
bellapy/training/__init__.py
bellapy/utils/__init__.py
bellapy-1.0.0.dist-info/licenses/LICENSE
bellapy-1.0.0.dist-info/METADATA
bellapy-1.0.0.dist-info/WHEEL
bellapy-1.0.0.dist-info/entry_points.txt
bellapy-1.0.0.dist-info/top_level.txt
bellapy-1.0.0.dist-info/RECORD
