Metadata-Version: 2.4
Name: bellapy
Version: 1.0.0
Summary: ML data toolkit - 29 features for dataset processing
Home-page: https://github.com/JuiceB0xC0de/bellapy
Author: Chiggy
Author-email: 
Keywords: machine-learning ml data-processing llm dataset bellapy
Classifier: Development Status :: 5 - Production/Stable
Classifier: Intended Audience :: Developers
Classifier: Topic :: Scientific/Engineering :: Artificial Intelligence
Classifier: License :: OSI Approved :: MIT License
Classifier: Programming Language :: Python :: 3
Classifier: Programming Language :: Python :: 3.8
Classifier: Programming Language :: Python :: 3.9
Classifier: Programming Language :: Python :: 3.10
Classifier: Programming Language :: Python :: 3.11
Requires-Python: >=3.8
License-File: LICENSE
Requires-Dist: rich>=13.0.0
Requires-Dist: pyyaml>=6.0
Requires-Dist: openai>=1.0.0
Requires-Dist: tiktoken>=0.5.0
Requires-Dist: click>=8.0.0
Provides-Extra: training
Requires-Dist: modal>=0.63.0; extra == "training"
Requires-Dist: transformers>=4.30.0; extra == "training"
Requires-Dist: torch>=2.0.0; extra == "training"
Requires-Dist: peft>=0.5.0; extra == "training"
Requires-Dist: trl>=0.7.0; extra == "training"
Requires-Dist: datasets>=2.14.0; extra == "training"
Requires-Dist: accelerate>=0.20.0; extra == "training"
Requires-Dist: bitsandbytes>=0.41.0; extra == "training"
Provides-Extra: dev
Requires-Dist: pytest>=7.0.0; extra == "dev"
Requires-Dist: pytest-cov>=4.0.0; extra == "dev"
Requires-Dist: black>=23.0.0; extra == "dev"
Requires-Dist: ruff>=0.1.0; extra == "dev"
Requires-Dist: mypy>=1.0.0; extra == "dev"
Provides-Extra: export
Requires-Dist: pandas>=2.0.0; extra == "export"
Requires-Dist: pyarrow>=14.0.0; extra == "export"
Dynamic: author
Dynamic: classifier
Dynamic: description
Dynamic: description-content-type
Dynamic: home-page
Dynamic: keywords
Dynamic: license-file
Dynamic: provides-extra
Dynamic: requires-dist
Dynamic: requires-python
Dynamic: summary
